[
    {
        "subject": "Placeholder",
        "description": "https://www.epochconverter.com",
        "timestamp": 0
    },
    {
        "subject": "Test 1 3.",
        "description": "https://www.epochconverter.com",
        "timestamp": 1721146049
    },
    {
        "subject": "Test 2 3.",
        "description": "https://www.epochconverter.com",
        "timestamp": 1721146049
    },
    {
        "subject": "Test 3 3.",
        "description": "https://www.epochconverter.com",
        "timestamp": 1723824449
    }
]
